wagtailadminintercom/__init__.py
wagtailadminintercom/_version.py
wagtailadminintercom/apps.py
wagtailadminintercom/conf.py
wagtailadminintercom/templates/wagtailadmin/admin_base.html
wagtailadminintercom/templates/wagtailadminintercom/intercom_scripts.html
wagtailadminintercom/templatetags/__init__.py
wagtailadminintercom/templatetags/wagtailadminintercom_tags.py
wagtailadminintercom-0.1.1.dist-info/DESCRIPTION.rst
wagtailadminintercom-0.1.1.dist-info/METADATA
wagtailadminintercom-0.1.1.dist-info/RECORD
wagtailadminintercom-0.1.1.dist-info/WHEEL
wagtailadminintercom-0.1.1.dist-info/metadata.json
wagtailadminintercom-0.1.1.dist-info/top_level.txt
