Metadata-Version: 2.0
Name: wagtailadminintercom
Version: 0.1.1
Summary: Add an Intercom chat widget inside the Wagtail admin
Home-page: https://github.com/takeflight/wagtailadminintercom
Author: Tim Heap
Author-email: tim@takeflight.com.au
License: BSD License
Platform: UNKNOWN
Classifier: Environment :: Web Environment
Classifier: Intended Audience :: Developers
Classifier: Operating System :: OS Independent
Classifier: Programming Language :: Python
Classifier: Framework :: Django
Classifier: License :: OSI Approved :: BSD License
Requires-Dist: wagtail (>=1.9)
